CHANGES
MANIFEST.in
setup.py
TracPyTppTheme.egg-info/PKG-INFO
TracPyTppTheme.egg-info/SOURCES.txt
TracPyTppTheme.egg-info/dependency_links.txt
TracPyTppTheme.egg-info/entry_points.txt
TracPyTppTheme.egg-info/requires.txt
TracPyTppTheme.egg-info/top_level.txt
pydotorgtheme/__init__.py
pydotorgtheme/theme.py
pydotorgtheme/htdocs/.pytpp.css.swp
pydotorgtheme/htdocs/button-on-bg.png
pydotorgtheme/htdocs/header-bg2.png
pydotorgtheme/htdocs/nav-off-.png
pydotorgtheme/htdocs/nav-on-b.png
pydotorgtheme/htdocs/pytpp.css
pydotorgtheme/htdocs/screenshot.png
pydotorgtheme/htdocs/screenshot_2.1.0.png
pydotorgtheme/templates/pytpp_theme.html