Metadata-Version: 1.0
Name: TracPyTppTheme
Version: 2.2.1
Summary: Trac theme based on python.org and The Python Papers.
Home-page: http://trac-hacks.org/wiki/PyTppThemePlugin
Author: Olemis Lang
Author-email: flioops.project@gmail.com
License: BSD
Keywords: trac plugin theme
Platform: UNKNOWN
Classifier: Framework :: Trac
